Duc/AdvancedPoint.py
Duc/AppState.py
Duc/BezierPoint.py
Duc/BinaryFileData.py
Duc/BinaryFiles.py
Duc/BinaryFilesEntry.py
Duc/BindingPoint.py
Duc/BoundElement.py
Duc/DucElement.py
Duc/DucGroup.py
Duc/ElementBackground.py
Duc/ElementContentBase.py
Duc/ElementStroke.py
Duc/ExportedDataState.py
Duc/ImageCrop.py
Duc/Point.py
Duc/PointBinding.py
Duc/SimplePoint.py
Duc/StrokeSides.py
Duc/StrokeStyle.py
Duc/TilingProperties.py
Duc/__init__.py
duc_py-0.1.0.dist-info/METADATA
duc_py-0.1.0.dist-info/WHEEL
duc_py-0.1.0.dist-info/top_level.txt
duc_py-0.1.0.dist-info/RECORD
