Metadata-Version: 2.1
Name: duc-py
Version: 0.1.0
Requires-Dist: flatbuffers
Requires-Dist: nanoid
